covemda/__init__.py
covemda/baseline_estimator.py
covemda/data_structure.py
covemda/integration.py
covemda/regressor.py
covemda/visualizer.py
CoVEMDA-1.0.dist-info/METADATA
CoVEMDA-1.0.dist-info/WHEEL
CoVEMDA-1.0.dist-info/top_level.txt
CoVEMDA-1.0.dist-info/RECORD
