Metadata-Version: 2.1
Name: CoVEMDA
Version: 1.0
Summary: CoronaVirus - Electricity Market Data Analyzer (CoVEMDA)
Home-page: https://github.com/tamu-engineering-research/COVID-EMDA
Author: Guangchun Ruan
Author-email: rgcthu@163.com
License: UNKNOWN
Keywords: COVID-19,extreme event,impact assessment,power system operation,power system resilience,cross-domain analysis
Platform: UNKNOWN
Classifier: Development Status :: 4 - Beta
Classifier: Programming Language :: Python :: 3
Classifier: Operating System :: Microsoft :: Windows
Classifier: License :: OSI Approved :: MIT License 
Requires-Python: >=3.5
Requires-Dist: pandas (>=1.2.4)
Requires-Dist: scipy (>=1.6.2)
Requires-Dist: statsmodels (>=0.12.2)
Requires-Dist: scikit-learn (>=0.24.1)
Requires-Dist: matplotlib (>=3.3.4)
